CONTRIBUTORS.rst
HISTORY.rst
LICENSE.txt
MANIFEST.in
README.rst
setup.cfg
setup.py
pycelle/__init__.py
pycelle/_caalgo.pyx
pycelle/_lightcones.pyx
pycelle/eca.py
pycelle/exceptions.py
pycelle/misc.py
pycelle.egg-info/PKG-INFO
pycelle.egg-info/SOURCES.txt
pycelle.egg-info/dependency_links.txt
pycelle.egg-info/requires.txt
pycelle.egg-info/top_level.txt