Metadata-Version: 1.1
Name: pycelle
Version: 0.0.1
Summary: Python package for cellular automata.
Home-page: https://github.com/ComSciCtr/pycelle
Author: pycelle developers
Author-email: UNKNOWN
License: BSD
Platform: UNKNOWN
Classifier: Development Status :: 3 - Alpha
Classifier: Intended Audience :: Developers
Classifier: Programming Language :: Python :: 2.6
Classifier: Programming Language :: Python :: 2.7
Classifier: Programming Language :: Python :: 3.2
Classifier: Programming Language :: Python :: 3.3
Classifier: Programming Language :: Python :: 3.4
Provides: pycelle
